gwcosmo/__init__.py
gwcosmo/create_injections.py
gwcosmo/injections.py
gwcosmo/data/A+_strain.txt
gwcosmo/data/H1_O1_strain.txt
gwcosmo/data/H1_O2_strain.txt
gwcosmo/data/H1_O3_strain.txt
gwcosmo/data/H1_O4a_avg.txt
gwcosmo/data/H1_O4b_avg.txt
gwcosmo/data/H1_O4high_strain.txt
gwcosmo/data/H1_O4low_strain.txt
gwcosmo/data/H1_O5_strain.txt
gwcosmo/data/K1_O4high_strain.txt
gwcosmo/data/K1_O4low_strain.txt
gwcosmo/data/K1_O5_strain.txt
gwcosmo/data/L1_O1_strain.txt
gwcosmo/data/L1_O2_strain.txt
gwcosmo/data/L1_O3_strain.txt
gwcosmo/data/L1_O4a_avg.txt
gwcosmo/data/L1_O4b_avg.txt
gwcosmo/data/L1_O4high_strain.txt
gwcosmo/data/L1_O4low_strain.txt
gwcosmo/data/L1_O5_strain.txt
gwcosmo/data/PSD_L1_H1_mid.txt
gwcosmo/data/README
gwcosmo/data/V1_O2_strain.txt
gwcosmo/data/V1_O3_strain.txt
gwcosmo/data/V1_O4b_avg.txt
gwcosmo/data/V1_O4high_strain.txt
gwcosmo/data/V1_O4low_strain.txt
gwcosmo/data/V1_O5_strain.txt
gwcosmo/data/aligo_O4high.txt
gwcosmo/data/avirgo_O4high_NEW.txt
gwcosmo/data/parameter_dictionary.json
gwcosmo/likelihood/__init__.py
gwcosmo/likelihood/bright_siren_likelihood.py
gwcosmo/likelihood/dark_siren_likelihood.py
gwcosmo/likelihood/posterior_samples.py
gwcosmo/likelihood/skymap.py
gwcosmo/maps/create_mth_map.py
gwcosmo/maps/create_norm_map.py
gwcosmo/plotting/__init__.py
gwcosmo/plotting/plot.py
gwcosmo/prior/LOS_redshift_prior.py
gwcosmo/prior/__init__.py
gwcosmo/prior/catalog.py
gwcosmo/prior/custom_math_priors.py
gwcosmo/prior/priors.py
gwcosmo/utilities/__init__.py
gwcosmo/utilities/arguments.py
gwcosmo/utilities/cache.py
gwcosmo/utilities/calc_kcor.py
gwcosmo/utilities/check_boundary.py
gwcosmo/utilities/cosmology.py
gwcosmo/utilities/gracedb.py
gwcosmo/utilities/host_galaxy_merger_relations.py
gwcosmo/utilities/injections_utilities.py
gwcosmo/utilities/luminosity_function.py
gwcosmo/utilities/mass_prior_utilities.py
gwcosmo/utilities/posterior_utilities.py
gwcosmo/utilities/redshift_utilities.py
gwcosmo/utilities/schechter_params.py
gwcosmo-3.0.0.dist-info/licenses/LICENSE.md
gwcosmo-3.0.0.dist-info/METADATA
gwcosmo-3.0.0.dist-info/WHEEL
gwcosmo-3.0.0.dist-info/top_level.txt
gwcosmo-3.0.0.dist-info/RECORD
