Metadata-Version: 2.4
Name: gwcosmo
Version: 3.0.0
Summary: A package to estimate cosmological parameters using gravitational-wave observations
Author-email: Rachel Gray <rachel.gray@ligo.org>
Project-URL: Homepage, https://git.ligo.org/lscsoft/gwcosmo
Project-URL: Documentation, https://lscsoft.docs.ligo.org/gwcosmo/
Classifier: Programming Language :: Python :: 3
Classifier: License :: OSI Approved :: GNU General Public License (GPL)
Classifier: Operating System :: OS Independent
Requires-Python: >=3.8
License-File: LICENSE.md
Requires-Dist: astropy
Requires-Dist: bilby
Requires-Dist: h5py
Requires-Dist: healpy==1.17.3
Requires-Dist: lalsuite
Requires-Dist: ligo-gracedb
Requires-Dist: ligo-segments
Requires-Dist: ligo.skymap<=1.0.7
Requires-Dist: lscsoft-glue
Requires-Dist: matplotlib>=2.0
Requires-Dist: multiprocess
Requires-Dist: numpy<=1.23.5,>=1.19
Requires-Dist: pandas
Requires-Dist: pesummary
Requires-Dist: progressbar
Requires-Dist: scipy==1.13.1
Requires-Dist: seaborn
Requires-Dist: tqdm
Requires-Dist: nessai==0.12.0
Dynamic: license-file
